jsonmask_ng/__init__.py
jsonmask_ng/mask.py
jsonmask_ng/parsing.py
jsonmask_ng/tests/__init__.py
jsonmask_ng/tests/conftest.py
jsonmask_ng/tests/test_mask.py
jsonmask_ng/tests/test_parsing.py
jsonmask_ng-0.4.5.dist-info/LICENSE.md
jsonmask_ng-0.4.5.dist-info/METADATA
jsonmask_ng-0.4.5.dist-info/WHEEL
jsonmask_ng-0.4.5.dist-info/RECORD
