Metadata-Version: 2.1
Name: jsonmask-ng
Version: 0.4.5
Summary: Implements the Google Partial Response protocol in Python
Home-page: https://github.com/juanyque/jsonmask_ng
License: MIT
Keywords: jsonmask_ng,jsonmask,json,google partial response
Author: Juan Garcia Longaron
Author-email: juan.mobilife@gmail.com
Requires-Python: >=3.7,<3.12
Classifier: Development Status :: 3 - Alpha
Classifier: License :: OSI Approved :: MIT License
Classifier: Natural Language :: English
Classifier: Operating System :: OS Independent
Classifier: Programming Language :: Python
Classifier: Programming Language :: Python :: 3
Classifier: Programming Language :: Python :: 3.7
Classifier: Programming Language :: Python :: 3.8
Classifier: Programming Language :: Python :: 3.9
Classifier: Programming Language :: Python :: 3.10
Classifier: Programming Language :: Python :: 3.11
Project-URL: Documentation, https://github.com/juanyque/jsonmask_ng/blob/master/README.md
Project-URL: Repository, https://github.com/juanyque/jsonmask_ng
